jmestts/__init__.py
jmestts/cli.py
jmestts/pricing.py
jmestts/tts.py
jmestts/voices.py
jmes_tts-0.0.2.dist-info/METADATA
jmes_tts-0.0.2.dist-info/WHEEL
jmes_tts-0.0.2.dist-info/entry_points.txt
jmes_tts-0.0.2.dist-info/licenses/LICENSE
jmes_tts-0.0.2.dist-info/licenses/NOTICE
jmes_tts-0.0.2.dist-info/RECORD
