Metadata-Version: 2.4
Name: jmes-tts
Version: 0.0.2
Summary: Generate audio from text documents
Author-email: James Saryerwinnie <js@jamesls.com>
License-Expression: Apache-2.0
License-File: LICENSE
License-File: NOTICE
Classifier: Development Status :: 3 - Alpha
Classifier: Intended Audience :: Developers
Classifier: Operating System :: OS Independent
Classifier: Programming Language :: Python
Classifier: Programming Language :: Python :: 3
Classifier: Programming Language :: Python :: 3.12
Classifier: Topic :: Software Development :: Libraries :: Python Modules
Classifier: Typing :: Typed
Requires-Python: >=3.12.0
Requires-Dist: boto3-stubs[polly,s3]<2.0.0,>=1.34.133
Requires-Dist: boto3<2.0.0,>=1.34.133
Requires-Dist: botocore-stubs<2.0.0,>=1.34.132
Requires-Dist: typer<0.22.0,>=0.20.0
